Workbook
Name Cost_of_Debt: Valuation!$C$7
Name Cost_of_Equity: Valuation!$C$5
Name Market_Risk_Premium: Valuation!$C$10
Name Risk_Free_Rate: Valuation!$C$9
Name Terminal_Growth_Rate: Valuation!$C$12
Name WACC: Valuation!$C$13
Name Weight_of_Debt: Valuation!$C$8
Name Weight_of_Equity: Valuation!$C$6
Name βeta: Valuation!$C$4

Sheet Exhibit 9
B2: Wrigley Selected Financial Data (in millions)
B4: Operating Data | C4: 2003 | D4: 2004 | E4: 2005 | F4: 2006 | G4: 2007
B5: Revenues | C5: 3069.09 | D5: 3648.59 | E5: 4159.31 | F5: 4686.01 | G5: 5389.1
B6: Gross profit | C6: 1792.35 | D6: 2038.61 | E6: 2255.9 | F6: 2429.82 | G6: 2840.78
B7: Income taxes | C7: 205.65 | D7: 227.54 | E7: 237.41 | F7: 239.67 | G7: 300.16
B8: Net Earnings | C8: 445.89 | D8: 492.95 | E8: 517.25 | F8: 529.38 | G8: 632.01
B9: Per share of common stock (diluted) | C9: 1.59 | D9: 1.75 | E9: 1.83 | F9: 1.9 | G9: 2.28
B11: Dividends Paid | C11: 2003 | D11: 2004 | E11: 2005 | F11: 2006 | G11: 2007
B12: Per share of common stock | C12: 0.69 | D12: 0.74 | E12: 0.86 | F12: 0.99 | G12: 1.13
B13: As a Percentage of Net Earnings | C13: 0.44 | D13: 0.42 | E13: 0.47 | F13: 0.52 | G13: 0.49
B14: Average shares outstanding | C14: 281204 | D14: 280796 | E14: 280964 | F14: 277556 | G14: 275357
B16: Other Financial Data | C16: 2003 | D16: 2004 | E16: 2005 | F16: 2006 | G16: 2007
B17: Net property, plant and equipment | C17: 956.18 | D17: 1142.62 | E17: 1282.41 | F17: 1422.52 | G17: 1560.06
... B25: Sales per employee | C25: 0.26 | D25: 0.25 | E25: 0.29 | F25: 0.3 | G25: 0.33

Sheet Exhibit 10
B2: Confectionary Industry at the Beginning of 2008 (in millions)
B4: Companies | C4: Revenues | D4: Operating Margin | E4: Net Income | F4: EBIT | G4: Long-Term Debt | H4: Current Assets | I4: Current Liabilities | J4: Employees
B5: Cadbury plc | C5: 15855 | D5: 0.132 | E5: 1567 | F5: 2088 | G5: 2383 | H5: 5171 | I5: 9178 | J5: 36460
B6: Kraft Foods Inc. | C6: 37000 | D6: 0.165 | E6: 2850 | F6: 6105 | G6: 10600 | H6: 9544 | I6: 10194 | J6: 90000
B7: Lance, Inc. | C7: 765 | D7: 0.09 | E7: 25 | F7: 68.85 | G7: 50 | H7: 142 | I7: 77 | J7: 4800
B8: The Hershey Company | C8: 4947 | D8: 0.24 | E8: 480 | F8: 1187.28 | G8: 1280 | H8: 1427 | I8: 1619 | J8: 12800
B9: Tootsie Roll Industries, Inc. | C9: 493 | D9: 0.2 | E9: 55 | F9: 98.6 | G9: 0 | H9: 233 | I9: 77 | J9: 1950
B10: Wm. Wrigley Jr. Company | C10: 5389 | D10: 0.179 | E10: 632 | F10: 962.77 | G10: 1000 | H10: 1579 | I10: 1189 | J10: 16400
B11: General Mills, Inc. | C11: 11640 | D11: 0.208 | E11: 1144 | F11: 2421.12 | G11: 3599 | H11: 3844 | I11: 6223 | J11: 28500
B12: Mars, Incorporated | C12: 25000 | D12: N/A | E12: N/A | F12: N/A | G12: N/A | H12: N/A | I12: N/A | J12: 48000
B14: Companies | C14: Market Cap | D14: Shares | E14: Stock Price | F14: PE Ratio | G14: Bond Rating | H14: βeta | I14: Dividend Yield | J14: Tax Rate
B15: Cadbury plc | C15: 26046 | D15: 2109000000 | E15: 12.35 | F15: 16.6 | G15: Aa | H15: 0.95 | I15: 0.021 | J15: 0.3
B16: Kraft Foods Inc. | C16: 46230 | D16: 1547200000 | E16: 29.88 | F16: 16.2 | G16: Aaa | H16: 0.75 | I16: 0.036 | J16: 0.355
B17: Lance, Inc. | C17: 594 | D17: 31204418 | E17: 19.05 | F17: 23.8 | G17: N/A | H17: 0.9 | I17: 0.034 | J17: 0.37
B18: The Hershey Company | C18: 8144 | D18: 227049657 | E18: 35.87 | F18: 17 | G18: Aa | H18: 0.7 | I18: 0.033 | J18: 0.36
B19: Tootsie Roll Industries, Inc. | C19: 1368 | D19: 54941131 | E19: 24.9 | F19: 24.9 | G19: N/A | H19: 0.85 | I19: 0.013 | J19: 0.33
B20: Wm. Wrigley Jr. Company | C20: 15899 | D20: 275742319 | E20: 57.66 | F20: 25.2 | G20: A | H20: 0.7 | I20: 0.022 | J20: 0.32
B21: General Mills, Inc. | C21: 17761 | D21: 336000000 | E21: 52.86 | F21: 15.5 | G21: A | H21: 0.65 | I21: 0.031 | J21: 0.343
B23: Growth Rate of Mature Company | D23: 0.056

Sheet Exhibit 11 and 12
B2: Financial forecast for Wrigley, Stand-Alone Valuation (in millions)
B4: Item | C4: 2006 | D4: 2007 | E4: 2008F | F4: 2009F | G4: 2010F | H4: 2011F | I4: 2012F
B5: Sugar prices (dollar/tonne) | C5: 416 | D5: 288 | E5: 293 | F5: 303 | G5: 312 | H5: 322 | I5: 331
B6: Sugar (in millions of tonnes) | C6: 1.5948 | D6: 2.6387 | E6: 2.9266 | F6: 3.0203 | G6: 3.1008 | H6: 3.1792 | I6: 3.2717
M7: Corporate Bonds | P7: Treasury Bills
B8: Revenue by Regions | M8: Aaa | N8: 0.0555 | P8: 1m | Q8: 0.0107
B9: North America | C9: 1822 | D9: 1823 | E9: 2011 | F9: 2096 | G9: 2183 | H9: 2265 | I9: 2353 | M9: Aa | N9: 0.0593 | P9: 3m | Q9: 0.0131
B10: EMEAI | C10: 2153 | D10: 2726 | E10: 3080 | F10: 3472 | G10: 3882 | H10: 4357 | I10: 4879 | M10: A | N10: 0.063 | P10: 6m | Q10: 0.0158
B11: Asia | C11: 648 | D11: 777 | E11: 876 | F11: 965 | G11: 1061 | H11: 1168 | I11: 1287 | M11: Baa | N11: 0.0697 | P11: 1y | Q11: 0.0174
B12: All other | C12: 63 | D12: 63 | E12: 72 | F12: 79 | G12: 90 | H12: 103 | I12: 117 | P12: 2y | Q12: 0.0205
B13: Revenues | C13: 4686 | D13: 5389 | E13: 6039 | F13: 6613 | G13: 7215 | H13: 7893 | I13: 8635 | P13: 3y | Q13: 0.0223
B14: COGS | P14: 5y | Q14: 0.0284
B15: Sugar | C15: 0 | D15: 761 | E15: 857 | F15: 915 | G15: 967 | H15: 1024 | I15: 1083 | P15: 7y | Q15: 0.0319
B16: Other | C16: 0 | D16: 1775 | E16: 2047 | F16: 2278 | G16: 2515 | H16: 2795 | I16: 3098 | P16: 10y | Q16: 0.0368
B17: Total COGS | C17: 0 | D17: 2535 | E17: 2904 | F17: 3193 | G17: 3483 | H17: 3818 | I17: 4181 | M17: Market Risk Premium | N17: 0.06 | P17: 20y | Q17: 0.044
B18: SG&A | C18: 0 | D18: 1891 | E18: 2114 | F18: 2315 | G18: 2525 | H18: 2755 | I18: 3005 | P18: 30y | Q18: 0.0444
B19: Operating income | C19: 0 | D19: 963 | E19: 1021 | F19: 1105 | G19: 1207 | H19: 1320 | I19: 1449
B20: NOPAT | C20: 0 | D20: 655 | E20: 694 | F20: 751 | G20: 821 | H20: 898 | I20: 986
B21: Depreciation | C21: 0 | D21: 51 | E21: 193 | F21: 156 | G21: 158 | H21: 163 | I21: 160
B22: Capital Expenditure | C22: 0 | D22: 189 | E22: 325 | F22: 340 | G22: 356 | H22: 373 | I22: 390
B23: Changes in NWC | C23: 0 | D23: -5 | E23: 134 | F23: -41 | G23: 40 | H23: 50 | I23: 30
B24: FCF | C24: 0 | D24: 0 | E24: 428 | F24: 608 | G24: 583 | H24: 638 | I24: 726
B26: Net PPE | C26: 1423 | D26: 1560 | E26: 1692 | F26: 1876 | G26: 2074 | H26: 2284 | I26: 2513
B27: % of Sales | C27: 0.304 | D27: 0.289 | E27: 0.28 | F27: 0.284 | G27: 0.287 | H27: 0.289 | I27: 0.291
B28: NWC | C28: 454.1 | D28: 448.66 | E28: 582.3 | F28: 541.77 | G28: 581.93 | H28: 631.52 | I28: 661.76
B29: % of Sales | C29: 0.097 | D29: 0.083 | E29: 0.096 | F29: 0.082 | G29: 0.081 | H29: 0.08 | I29: 0.077
B31: Tax rate | C31: 0.32

Sheet Valuation
B3: Valuation Inputs | E3: Discounted Cash Flow Model
B4: βeta | C4: ='Exhibit 10'!H20 -> 0.7 | E4: Year | F4: 1 | G4: 2 | H4: 3 | I4: 4 | J4: 5 | K4: 6 and Beyond…
B5: Cost of Equity | C5: =Risk_Free_Rate+(βeta*Market_Risk_Premium) -> 0.0788 | E5: Items | F5: 2008 | G5: 2009 | H5: 2010 | I5: 2011 | J5: 2012 | K5: Terminal Value
B6: Weight of Equity | C6: =('Exhibit 10'!C20/('Exhibit 10'!C20+'Exhibit 10'!G10)) -> 0.9408249 | E6: Free Cash Flows | F6: ='Exhibit 11 and 12'!E24 -> 428 | G6: ='Exhibit 11 and 12'!F24 -> 608 | H6: ='Exhibit 11 and 12'!G24 -> 583 | I6: ='Exhibit 11 and 12'!H24 -> 638 | J6: ='Exhibit 11 and 12'!I24 -> 726 | K6: =(J6*(1+Terminal_Growth_Rate))/(WACC-Terminal_Growth_Rate) -> 37086.573 | AA6: Other groups content
B7: Cost of Debt | C7: ='Exhibit 11 and 12'!N10 -> 0.063 | E7: Discount Factor | F7: =1/(1+WACC)^F4 -> 0.92878791 | G7: =1/(1+WACC)^G4 -> 0.86264699 | H7: =1/(1+WACC)^H4 -> 0.8012161 | I7: =1/(1+WACC)^I4 -> 0.74415983 | J7: =1/(1+WACC)^J4 -> 0.69116665 | K7: =1/(1+WACC)^J4 -> 0.69116665 | Z7: Slide No. | AA7: TIFFANY - Tejasvee, prachi, anshika, rhea | AC7: LVMH | AD7: tifany - yash khanter, rishav, nithin
B8: Weight of Debt | C8: =1-C6 -> 0.059175099 | E8: Present Value | F8: =F6*F7 -> 397.52123 | G8: =G6*G7 -> 524.48937 | H8: =H6*H7 -> 467.10899 | I8: =I6*I7 -> 474.77397 | J8: =J6*J7 -> 501.78699 | K8: =K6*K7 -> 25633.003 | Z8: 1 | AA8: Business overview | AC8: short description | AD8: current financial situation
B9: Risk-Free Rate (10 year) | C9: ='Exhibit 11 and 12'!Q16 -> 0.0368 | Z9: 2 | AA9: Industry overview | AC9: table of contents | AD9: very brief history of lvmh and tiffany
B10: Market Risk Premium | C10: ='Exhibit 11 and 12'!N17 -> 0.06 | Z10: 3 | AA10: Rationale for acquisition (Tiffany Viewpoint) | AC10: background of lvmh | AD10: ranking of peers and itself
B11: Tax Rate | C11: ='Exhibit 11 and 12'!C31 -> 0.32 | Z11: 4 | AA11: Rationale for acquisition (LVMH viewpoint) | AC11: background of tiffany | AD11: peer market share
B12: Terminal Growth Rate | C12: ='Exhibit 10'!D23 -> 0.056 | E12: Valuation | Z12: 5 | AA12: Pre and post financial comparison | AC12: tiffany financial position | AD12: why acquired only tiffany, why not others
B13: WACC | C13: =(C5*C6)+(C7*C8*(1-C11)) -> 0.076672063 | E13: Enterprise Value | F13: =SUM(F8:K8) -> 27998.683 | L13: Share Price Sensitivity Analysis | Z13: 6 | AA13: Valuation of tiffany (EV multiples and per share value bar graph) | AC13: competition analysis | AD13: bulgari info
E14: (-) Debt Value | F14: =C19 -> 1000 | L14: Current Share Price | N14: Terminal Growth Rate | AC14: lvmh group revenue composition | AD14: success of bulgari
E15: (+) Cash and Cash Equivalents | F15: =C18 -> 157.9 | L15: =F18 -> 98.485367 | N15: 0.03 | O15: 0.04 | P15: 0.05 | Q15: 0.056 | R15: 0.06 | Z15: 7 | AA15: Valuation methodology and key assumptions | AC15: geographic revenue breakdown | AD15: what tiffany brings to lvmh, mostly bar graph
B16: Equity Value Calculation Inputs | E16: Equity Value | F16: =F13+F15-F14 -> 27156.583 | L16: WACC | M16: 0.055 | N16: 89.079238 | O16: 145.75431 | P16: 429.12968 | Q16: NM | R16: NM | Z16: 8 | AA16: Deal Conditions | AC16: tiffany Balance sheet | AD16: brief geographic situation
B17: Current Assets | C17: ='Exhibit 10'!H10 -> 1579 | E17: Shares Outstanding | F17: ='Exhibit 10'!D20 -> 275742319 | H17: Net Income | I17: ='Exhibit 10'!E10*1000000 -> 632000000 | M17: 0.06 | N17: 73.497285 | O17: 108.25558 | P17: 212.53047 | Q17: 525.35514 | R17: NM | Z17: 9 | AA17: final recommendation | AC17: tiffany income statement | AD17: valuation summary
B18: Cash (10% Curr. Assets) | C18: =0.1*C17 -> 157.9 | E18: Price Per Share | F18: =(F16*1000000)/F17 -> 98.485367 | H18: EPS | I18: =I17/F17 -> 2.2919949 | M18: 0.065 | N18: 62.370901 | O18: 85.760712 | P18: 140.33694 | Q18: 231.29731 | R18: 413.21807 | Z18: 10 | AA18: THANK YOU | AC18: tiffany dcf | AD18: football field chart for valuation
B19: Debt | C19: ='Exhibit 10'!G10 -> 1000 | H19: EV/EBIT Multiple | I19: =F13/'Exhibit 10'!F10 -> 29.081383 | M19: 0.07 | N19: 54.029166 | O19: 70.767678 | P19: 104.2447 | Q19: 147.28659 | R19: 204.67577 | AC19: forecast assumptions | AD19: price position
H20: P/E Ratio | I20: =F18/I18 -> 42.969278 | M20: 0.0767 | N20: 45.655695 | O20: 57.086357 | P20: 77.079314 | Q20: 98.49 | R20: 121.01593 | AC20: WACC tiffany
M21: 0.08 | N21: 42.357825 | O21: 52.0341 | P21: 68.161224 | Q21: 84.288348 | R21: 100.41547 | AC21: combined valuation
AC22: combined dcf
AC23: combined cost of debt
AC24: combined WACC
AC25: industry beta and target d/e
AC26: fcf forecast
AC27: scenario analysis
AC28: valuation results
AC29: multiple valuation model
AC30: equity to enterprise value calculation
AC31: comparables valuation analysis
AC32: price range per share

Sheet Comps. Multiple Analysis
B2: Comparable Companies Multiple Analysis
B4: Companies | C4: Market Cap | D4: Net Income | E4: PE Ratio | F4: EBIT | G4: Cash | H4: Long-Term Debt | I4: EV | J4: EV/EBIT
B5: Cadbury plc | C5: 26046 | D5: 1567 | E5: 16.6 | F5: 2088 | G5: =0.1*'Exhibit 10'!H5 -> 517.1 | H5: 2383 | I5: =C5+H5-G5 -> 27911.9 | J5: =I5/F5 -> 13.367768
B6: Kraft Foods Inc. | C6: 46230 | D6: 2850 | E6: 16.2 | F6: 6105 | G6: =0.1*'Exhibit 10'!H6 -> 954.4 | H6: 10600 | I6: =C6+H6-G6 -> 55875.6 | J6: =I6/F6 -> 9.1524324
B7: Lance, Inc. | C7: 594 | D7: 25 | E7: 23.8 | F7: 68.85 | G7: =0.1*'Exhibit 10'!H7 -> 14.2 | H7: 50 | I7: =C7+H7-G7 -> 629.8 | J7: =I7/F7 -> 9.1474219
B8: The Hershey Company | C8: 8144 | D8: 480 | E8: 17 | F8: 1187.28 | G8: =0.1*'Exhibit 10'!H8 -> 142.7 | H8: 1280 | I8: =C8+H8-G8 -> 9281.3 | J8: =I8/F8 -> 7.8172798
B9: Tootsie Roll Industries, Inc. | C9: 1368 | D9: 55 | E9: 24.9 | F9: 98.6 | G9: =0.1*'Exhibit 10'!H9 -> 23.3 | H9: 0 | I9: =C9+H9-G9 -> 1344.7 | J9: =I9/F9 -> 13.637931
B10: General Mills, Inc. | C10: 17761 | D10: 1144 | E10: 15.5 | F10: 2421.12 | G10: =0.1*'Exhibit 10'!H11 -> 384.4 | H10: 3599 | I10: =C10+H10-G10 -> 20975.6 | J10: =I10/F10 -> 8.6635937
B12: Average | E12: =AVERAGE(E5:E10) -> 19 | J12: =AVERAGE(J5:J10) -> 10.297738
C15: EV/EBIT Multiple Comparison | G15: P/E Ratio Comparison
C16: Peers | E16: =J12 -> 10.297738 | G16: Peers | I16: =E12 -> 19
C17: Wrigley | E17: =('Exhibit 10'!C20+'Exhibit 10'!G10-'Exhibit 10'!H10*0.1)/'Exhibit 10'!F10 -> 17.388473 | G17: Wrigley | I17: ='Exhibit 10'!F20 -> 25.2

Sheet Synergy Forecast
B2: Financial forecast for Wrigley, Synergy Valuation (in millions) | L2: Synergies ($ in millions)
L3: EMEAI Revenue | M3: 0.04
B4: Item | C4: 2006 | D4: 2007 | E4: 2008F | F4: 2009F | G4: 2010F | H4: 2011F | I4: 2012F | L4: Asia Revenue | M4: 0.05
B5: Sugar prices (dollar/tonne) | C5: 416 | D5: 288 | E5: 293 | F5: 303 | G5: 312 | H5: 322 | I5: 331 | L5: SG&A Savings | M5: 0.09
B6: Sugar (in millions of tonnes) | C6: 1.5948 | D6: 2.6387 | E6: 2.9266 | F6: 3.0203 | G6: 3.1008 | H6: 3.1792 | I6: 3.2717
L7: NWC | M7: 0.15
B8: Revenue by Regions | L8: After Tax Savings | M8: 50
B9: North America | C9: 1822 | D9: 1823 | E9: 2011 | F9: 2096 | G9: 2183 | H9: 2265 | I9: 2353
B10: EMEAI | C10: 2153 | D10: 2726 | E10: 3080 | F10: 3472 | G10: 3882 | H10: 4357 | I10: 4879
B11: EMEAI Revenue w/ Synergy | C11: 0 | D11: 0 | E11: =E10*(1+$M$3) -> 3203.2 | F11: =F10*(1+$M$3) -> 3610.88 | G11: =G10*(1+$M$3) -> 4037.28 | H11: =H10*(1+$M$3) -> 4531.28 | I11: =I10*(1+$M$3) -> 5074.16
B12: Asia | C12: 648 | D12: 777 | E12: 876 | F12: 965 | G12: 1061 | H12: 1168 | I12: 1287
B13: Asia Revenue w/ Synergy | C13: 0 | D13: 0 | E13: =E12*(1+$M$4) -> 919.8 | F13: =F12*(1+$M$4) -> 1013.25 | G13: =G12*(1+$M$4) -> 1114.05 | H13: =H12*(1+$M$4) -> 1226.4 | I13: =I12*(1+$M$4) -> 1351.35
B14: All other | C14: 63 | D14: 63 | E14: 72 | F14: 79 | G14: 90 | H14: 103 | I14: 117
B15: Revenues | C15: 4686 | D15: 5389 | E15: =E9+E11+E13+E14 -> 6206 | F15: =F9+F11+F13+F14 -> 6799.13 | G15: =G9+G11+G13+G14 -> 7424.33 | H15: =H9+H11+H13+H14 -> 8125.68 | I15: =I9+I11+I13+I14 -> 8895.51
B16: COGS
B17: Sugar | C17: 0 | D17: 761 | E17: 857 | F17: 915 | G17: 967 | H17: 1024 | I17: 1083
B18: Other | C18: 0 | D18: 1775 | E18: 2047 | F18: 2278 | G18: 2515 | H18: 2795 | I18: 3098
B19: Total COGS | C19: 0 | D19: 2535 | E19: 2904 | F19: 3193 | G19: 3483 | H19: 3818 | I19: 4181
B20: SG&A | C20: 0 | D20: 1891 | E20: 2114 | F20: 2315 | G20: 2525 | H20: 2755 | I20: 3005
B21: SG&A w/ Synergy | C21: 0 | D21: =D20 -> 1891 | E21: =E20*(1-$M$5) -> 1923.74 | F21: =F20*(1-$M$5) -> 2106.65 | G21: =G20*(1-$M$5) -> 2297.75 | H21: =H20*(1-$M$5) -> 2507.05 | I21: =I20*(1-$M$5) -> 2734.55
B22: Operating income | C22: 0 | D22: 963 | E22: =E15-E19-E21 -> 1378.26 | F22: =F15-F19-F21 -> 1499.48 | G22: =G15-G19-G21 -> 1643.58 | H22: =H15-H19-H21 -> 1800.63 | I22: =I15-I19-I21 -> 1979.96
B23: NOPAT | C23: 0 | D23: 655 | E23: =E22*(1-$C$36) -> 937.2168 | F23: =F22*(1-$C$36) -> 1019.6464 | G23: =G22*(1-$C$36) -> 1117.6344 | H23: =H22*(1-$C$36) -> 1224.4284 | I23: =I22*(1-$C$36) -> 1346.3728
B24: Depreciation | C24: 0 | D24: 51 | E24: 193 | F24: 156 | G24: 158 | H24: 163 | I24: 160
B25: Capital Expenditure | C25: 0 | D25: 189 | E25: 325 | F25: 340 | G25: 356 | H25: 373 | I25: 390
B26: Changes in NWC | C26: 0 | D26: -5 | E26: 134 | F26: -41 | G26: 40 | H26: 50 | I26: 30
B27: One-Time NWC Reduction | C27: 0 | D27: 0 | E27: =E26*(1-$M$7) -> 113.9 | F27: 0 | G27: 0 | H27: 0 | I27: 0
B28: After-Tax Savings w/ Synergy | C28: 0 | D28: 0 | E28: =M8 -> 50 | F28: 0 | G28: 0 | H28: 0 | I28: 0
B29: FCF | C29: 0 | D29: 0 | E29: =E23+E24-E25-E27+E28 -> 741.3168 | F29: =F23+F24-F25-F26 -> 876.6464 | G29: =G23+G24-G25-G26 -> 879.6344 | H29: =H23+H24-H25-H26 -> 964.4284 | I29: =I23+I24-I25-I26 -> 1086.3728
B31: Net PPE | C31: 1423 | D31: 1560 | E31: 1692 | F31: 1876 | G31: 2074 | H31: 2284 | I31: 2513
B32: % of Sales | C32: 0.304 | D32: 0.289 | E32: =E31/E15 -> 0.27263938 | F32: =F31/F15 -> 0.27591765 | G32: =G31/G15 -> 0.27935181 | H32: =H31/H15 -> 0.28108417 | I32: =I31/I15 -> 0.28250207
B33: NWC | C33: 454.1 | D33: 448.66 | E33: 563 | F33: 522 | G33: 562 | H33: 612 | I33: 642
B34: % of Sales | C34: 0.097 | D34: 0.083 | E34: =E33/E15 -> 0.090718659 | F34: =F33/F15 -> 0.076774529 | G34: =G33/G15 -> 0.075697066 | H34: =H33/H15 -> 0.075316773 | I34: =I33/I15 -> 0.072171241
B36: Tax rate | C36: 0.32

Sheet Synergy Valuation
B2: Valuation Inputs | E2: Discounted Cash Flow Model
B3: βeta | C3: 0.7 | E3: Year | F3: 1 | G3: 2 | H3: 3 | I3: 4 | J3: 5 | K3: 6 & Beyond...
B4: Cost of Equity | C4: 0.0788 | E4: Items | F4: 2008 | G4: 2009 | H4: 2010 | I4: 2011 | J4: 2012 | K4: Terminal Value
B5: Weight of Equity | C5: 0.9408249 | E5: Free Cash Flows | F5: ='Synergy Forecast'!E29 -> 741.3168 | G5: ='Synergy Forecast'!F29 -> 876.6464 | H5: ='Synergy Forecast'!G29 -> 879.6344 | I5: ='Synergy Forecast'!H29 -> 964.4284 | J5: ='Synergy Forecast'!I29 -> 1086.3728 | K5: =J5*(1+C11)/(C12-C11) -> 55495.654
B6: Cost of Debt | C6: 0.063 | E6: Discount Factor | F6: =1/(1+$C$12)^F3 -> 0.92878791 | G6: =1/(1+$C$12)^G3 -> 0.86264699 | H6: =1/(1+$C$12)^H3 -> 0.8012161 | I6: =1/(1+$C$12)^I3 -> 0.74415983 | J6: =1/(1+$C$12)^J3 -> 0.69116665 | K6: =J6 -> 0.69116665
B7: Weight of Debt | C7: 0.059175099 | E7: Present Value | F7: =F5*F6 -> 688.52608 | G7: =G5*G6 -> 756.23638 | H7: =H5*H6 -> 704.77724 | I7: =I5*I6 -> 717.68887 | J7: =J5*J6 -> 750.86465 | K7: =K5*K6 -> 38356.745
B8: Risk-Free Rate (10 year) | C8: 0.0368
B9: Market Risk Premium | C9: 0.06
B10: Tax Rate | C10: 0.32 | E10: Valuation
B11: Terminal Growth Rate | C11: 0.056 | E11: Enterprise Value | F11: =SUM(F7:K7) -> 41974.839
B12: WACC | C12: 0.076672063 | E12: (-) Debt Value | F12: =C18 -> 1000
E13: (+) Cash and Cash Equivalents | F13: =C17 -> 157.9
E14: Equity Value | F14: =F11-F12+F13 -> 41132.739
B15: Equity Value Calculation Inputs | E15: Shares Outstanding | F15: ='Exhibit 10'!D20 -> 275742319
B16: Current Assets | C16: 1579 | E16: Price per Share | F16: =F14*1000000/F15 -> 149.17093
B17: Cash (10% Curr. Assets) | C17: 157.9
B18: Debt | C18: 1000
H21: Share Price Sensitivity Analysis
H22: Current Share Price | J22: Terminal Growth Rate
H23: =F16 -> 149.17093 | J23: 0.03 | K23: 0.04 | L23: 0.05 | M23: 0.056 | N23: 0.06
H24: WACC | I24: 0.055 | J24: 135.1 | K24: 219.91 | L24: 643.95 | M24: NM | N24: NM
I25: 0.06 | J25: 111.78 | K25: 163.8 | L25: 319.83 | M25: 787.94 | N25: NM
I26: 0.065 | J26: 95.13 | K26: 130.13 | L26: 211.8 | M26: 347.91 | N26: 620.13
I27: 0.07 | J27: 82.65 | K27: 107.7 | L27: 157.79 | M27: 222.2 | N27: 308.07
I28: 0.0767 | J28: 70.12 | K28: 87.22 | L28: 117.14 | M28: 149.17 | N28: 182.89
I29: 0.08 | J29: 65.18 | K29: 79.66 | L29: 103.79 | M29: 127.93 | N29: 152.06
